Metadata-Version: 2.1
Name: generalized-average
Version: 0.0.0.1
Summary: Calcalating different of averages for DL pooling tasks
Author: Uri Itai Alexander Molak &  Natan Katz
